vizhash
