Metadata-Version: 1.1
Name: vizhash
Version: 1.4.0
Summary: Python Visual Hash,generate a visual random image associated with a string.
Home-page: https://github.com/luxcem/vizhash
Author: luxcem
Author-email: a@luxcem.fr
License: UNKNOWN
Download-URL: https://github.com/luxcem/vizhash/tarball/1.4.0
Keywords: visual hash vizhash random maze identicon
Platform: UNKNOWN
Classifier: Programming Language :: Python :: 3
Classifier: Programming Language :: Python :: 3.2
Classifier: Programming Language :: Python :: 3.3
Classifier: Programming Language :: Python :: 3.4
